<?xml version="1.0" encoding="UTF-8"?>
<configuration>
    <springProperty scope="context" name="appName" source="spring.application.name" defaultValue="unknown"/>

    <appender name="CONSOLE" class="ch.qos.logback.core.ConsoleAppender">
        <encoder class="ch.qos.logback.classic.encoder.PatternLayoutEncoder">
            <pattern>{"timestamp":"%d{yyyy-MM-dd'T'HH:mm:ss.SSSZ}","level":"%level","service":"${appName}","traceId":"%X{traceId:-}","requestId":"%X{requestId:-}","userId":"%X{userId:-}","thread":"%thread","logger":"%logger{36}","message":"%message"%nopex}%n</pattern>
        </encoder>
    </appender>

    <appender name="FILE" class="ch.qos.logback.core.rolling.RollingFileAppender">
        <file>logs/${appName}.log</file>
        <rollingPolicy class="ch.qos.logback.core.rolling.TimeBasedRollingPolicy">
            <fileNamePattern>logs/${appName}.%d{yyyy-MM-dd}.log</fileNamePattern>
            <maxHistory>7</maxHistory>
        </rollingPolicy>
        <encoder class="ch.qos.logback.classic.encoder.PatternLayoutEncoder">
            <pattern>{"timestamp":"%d{yyyy-MM-dd'T'HH:mm:ss.SSSZ}","level":"%level","service":"${appName}","traceId":"%X{traceId:-}","requestId":"%X{requestId:-}","userId":"%X{userId:-}","thread":"%thread","logger":"%logger{36}","message":"%message"%nopex}%n</pattern>
        </encoder>
    </appender>

    <root level="INFO">
        <appender-ref ref="CONSOLE"/>
        <appender-ref ref="FILE"/>
    </root>
</configuration>
